pycorrel/__init__.py
pycorrel/copulas.py
pycorrel/pycorrel.py
pycorrel/utils.py
pycorrel-0.1.1.dist-info/AUTHORS.rst
pycorrel-0.1.1.dist-info/LICENSE
pycorrel-0.1.1.dist-info/METADATA
pycorrel-0.1.1.dist-info/WHEEL
pycorrel-0.1.1.dist-info/top_level.txt
pycorrel-0.1.1.dist-info/RECORD
