Metadata-Version: 2.1
Name: pycorrel
Version: 0.1.1
Summary: pycorrel provides methods to correlate random variables with arbitrary marginal distributions.
Home-page: https://github.com/maximegodin/pycorrel
Author: Maxime Godin
Author-email: maxime.godin@polytechnique.org
License: MIT license
Keywords: pycorrel
Platform: UNKNOWN
Classifier: Development Status :: 2 - Pre-Alpha
Classifier: Intended Audience :: Developers
Classifier: License :: OSI Approved :: MIT License
Classifier: Natural Language :: English
Classifier: Programming Language :: Python :: 3
Classifier: Programming Language :: Python :: 3.5
Classifier: Programming Language :: Python :: 3.6
Classifier: Programming Language :: Python :: 3.7
Classifier: Programming Language :: Python :: 3.8
Requires-Python: >=3.5
Requires-Dist: numpy
Requires-Dist: scipy
